src files/core_sobel.v
module core_sobel ( p0, p1, p2, p3, p5, p6, p7, p8, out);

input  [7:0] p0,p1,p2,p3,p5,p6,p7,p8;	// 8 bit pixels inputs
output [7:0] out;					// 8 bit output pixel

wire signed [10:0] gx,gy;    //11 bits because max value of gx and gy is 
//255*4 and last bit for sign					
wire signed [10:0] abs_gx,abs_gy;	//it is used to find the absolute value of gx and gy
wire [10:0] sum;			//the max value is 255*8. here no sign bit needed.

assign gx=((p2-p0)+((p5-p3)<<1)+(p8-p6));//sobel mask for gradient in horiz. direction
assign gy=((p0-p6)+((p1-p7))+(p2-p8));//sobel mask for gradient in vertical direction
// assign gx = (p2-p0)<<2;
// assign gx = 0;

assign abs_gx = (gx[10]? ~gx+1 : gx);	// to find the absolute value of gx.
assign abs_gy = (gy[10]? ~gy+1 : gy);	// to find the absolute value of gy. / bitwise negation +1 is 2's comp. of value.

assign sum = (abs_gx + abs_gy)/10; // < 50? 0 : (abs_gx + abs_gy);				// finding the sum with threshold 50
assign out = (|sum[10:8])?8'hff : sum[7:0];	// to limit the max value to 255 / sum[10]|sum[9]|sum[8]=1 then out=255 else: sum[7:0]

endmodule

src files/core_avg.v
module core_avg ( p0, p1, p2, p3, p4, p5, p6, p7, p8, out);

input  [7:0] p0, p1, p2, p3, p4, p5, p6, p7, p8;
output [7:0] out;					
wire [10:0] sum;	

assign sum = (p0+p1+p2+p3+p4+p5+p6+p7+p8)/9;    // Find the average of the pixel
assign out = (|sum[10:8])?8'hff : sum[7:0];	// to limit the max value to 255 (sum[10]|sum[9]|sum[8]=1 then out=255 else: sum[7:0])

endmodule

src files/average_grayscale_filter.v
module avgGrayscale (rgb_in, clk_i, reset, rgb_out, flag_grayscale_complete, flag_output_complete, taken_input, gray_output_done, sobel_output_done, avg_bus_in, sobel_bus_in);
    input wire [7:0] rgb_in;
    input wire clk_i;
    input wire reset;
    output wire [7:0] rgb_out;
    output reg flag_grayscale_complete;
    output reg flag_output_complete;

    parameter res_y = 32;
    parameter res_x = 32;

    integer i;

    reg [7:0] gray_mem [res_y-1:0][res_x-1:0];
    reg [7:0] avg_mem [res_y-1:0][res_x-1:0];
    reg [7:0] edge_mem [res_y-1:0][res_x-1:0];

    reg signed [7:0] r_channel [0:1023];
    reg signed [7:0] g_channel [0:1023];

    reg [12:0] counter;
    reg [7:0] debugger;
    output reg taken_input, gray_output_done, sobel_output_done;
    reg [10:0] row, col, a_row, a_col, b_row, b_col, c_row, c_col, d_row, d_col;

    reg [7:0] arow3 [2:0];
    reg [7:0] arow2 [2:0];
    reg [7:0] arow1 [2:0];

    reg [7:0] srow3 [2:0];
    reg [7:0] srow2 [2:0];
    reg [7:0] srow1 [2:0];

    output [7:0] avg_bus_in, sobel_bus_in;

    core_avg avg(arow1[0], arow1[1], arow1[2], arow2[0], arow2[1], arow2[2], arow3[0], arow3[1], arow3[2], avg_bus_in);
    core_sobel sobel(srow1[0], srow1[1], srow1[2], srow2[0], srow2[2], srow3[0], srow3[1], srow3[2], sobel_bus_in);
    assign rgb_out = sobel_bus_in;  // to be commented
    // assign rgb_out = avg_bus_in;

    always @(posedge clk_i) begin
        if(reset) begin
            counter <= 0;
            row <= 0;   col <= 0;
            a_row <= 0;     a_col <= 0;
            b_row <= 0;     b_col <= 0;
            c_row <= 0;     c_col <= 0;
            d_row <= 0;     d_col <= 0;
            flag_grayscale_complete <= 0;
            flag_output_complete <= 0;
            taken_input <= 0;
            gray_output_done <= 0;
            sobel_output_done <= 0;
        end
        else begin
            // if(!taken_input)
            // begin
                if(counter < (res_y*res_x)) begin                // take red inputs and store it in buffer
                    r_channel[counter] <= rgb_in;
                end
                if(counter >= (res_y*res_x-1) && counter < (2*res_y*res_x - 1)) begin           // take green inputs and store it in buffer
                    g_channel[counter - (res_y*res_x-1)] <= rgb_in;
                end
                if(counter >= (2*res_y*res_x - 1) && counter < (3*res_y*res_x - 1)) begin
                    gray_mem[row][col] <= (r_channel[counter - (2*res_y*res_x - 1)] * 30 + g_channel[counter - (2*res_y*res_x - 1)] * 59 + rgb_in * 11) / 100;;		// Converts into grayscale and writes to RAM
                    if (row <= res_y - 1) begin
                        col <= (col == res_x - 1)? 0 : col + 1;
                        row <= (col == res_x - 1)? row + 1 : row;
                    end
                    if(row == res_y - 1 && col == res_x - 1)begin
                        row <= 0;
                        col <= 0;
                    end
                end
                counter <= (counter==(3*res_y*res_x - 1))? 0 : counter + 1;
                if(counter==(3*res_y*res_x - 1))
                    taken_input <= 1;
            end
        // end
    end

    always@(posedge clk_i)          
    begin
        if(taken_input)             // Smoothen Function + Zero Padding
        begin
            avg_mem[a_row+1][a_col+1] <= avg_bus_in;		 // write the smoothen vaues to RAM
            for(i=0; i<res_y; i++)                                     
            begin        // Zero Padding 
                avg_mem[i][0] <= 0;
                avg_mem[i][res_x-1] <= 0;
            end
            for(i=0; i<res_x; i++)                                     
            begin        // Zero Padding 
                avg_mem[0][i] <= 0;
                avg_mem[res_y-1][i] <= 0;
            end
            // Writing indices for avg RAM
            if (a_row <= res_y - 3) begin
                a_col <= (a_col == res_x - 3)? 0 : a_col + 1;
                a_row <= (a_col == res_x - 3)? a_row + 1 : a_row;
            end
            if(a_row == res_y - 3 && a_col == res_x - 3)begin
                a_row <= 0;
                a_col <= 0;
            end
            // Reading indexes from gray RAM
            if (b_row <= res_y - 3) begin
			b_col <= (b_col == res_x - 3)? 0 : b_col + 1;
			b_row <= (b_col == res_x - 3)? b_row + 1 : b_row;
            end
            if(b_row == res_y - 3 && b_col == res_x - 3)begin
                b_row <= 0;
                b_col <= 0;
                gray_output_done <= 1;
            end
            {arow1[0], arow1[1], arow1[2], arow2[0], arow2[1], arow2[2], arow3[0], arow3[1], arow3[2]} <= {gray_mem[b_row][b_col],gray_mem[b_row][b_col+1],gray_mem[b_row][b_col+2],gray_mem[b_row+1][b_col],gray_mem[b_row+1][b_col+1],gray_mem[b_row+1][b_col+2],gray_mem[b_row+2][b_col],gray_mem[b_row+2][b_col+1],gray_mem[b_row+2][b_col+2]};
        end
        if(gray_output_done)                     // Edge Detect + Zero Padding
        begin
            edge_mem[c_row+1][c_col+1] <= sobel_bus_in;		 // write the smoothen vaues to RAM
            for(i=0; i<res_y; i++)                                     
            begin        // Zero Padding 
                edge_mem[i][0] <= 0;
                edge_mem[i][res_x-1] <= 0;
            end
            for(i=0; i<res_x; i++)                                     
            begin        // Zero Padding 
                edge_mem[0][i] <= 0;
                edge_mem[res_y-1][i] <= 0;
            end
            // Writing indices for sobel RAM
            if (c_row <= res_y - 3) begin
                c_col <= (c_col == res_x - 3)? 0 : c_col + 1;
                c_row <= (c_col == res_x - 3)? c_row + 1 : c_row;
            end
            if(c_row == res_y - 3 && c_col == res_x - 3)begin
                c_row <= 0;
                c_col <= 0;
            end
            // Reading indexes from avg RAM
            if (d_row <= res_y - 3) begin
			d_col <= (d_col == res_x - 3)? 0 : d_col + 1;
			d_row <= (d_col == res_x - 3)? d_row + 1 : d_row;
            end
            if(d_row == res_y - 3 && d_col == res_x - 3)begin
                d_row <= 0;
                d_col <= 0;
                sobel_output_done <= 1;
            end
            {srow1[0], srow1[1], srow1[2], srow2[0], srow2[2], srow3[0], srow3[1], srow3[2]} <= {avg_mem[d_row][d_col],avg_mem[d_row][d_col+1],avg_mem[d_row][d_col+2],avg_mem[d_row+1][d_col],avg_mem[d_row+1][d_col+2],avg_mem[d_row+2][d_col],avg_mem[d_row+2][d_col+1],avg_mem[d_row+2][d_col+2]};
        end
    end
endmodule

src files/tb.v
`timescale 1ns / 1ps
module tb();

reg [7:0] rgb_in;
reg clk_i;
reg rst_i;

wire flag_grayscale_complete;
reg tmp;
reg tmp2;
wire [7:0]rgb_out;
wire flag_output_complete;

// Flags form module
wire taken_input, gray_output_done, sobel_output_done;

// Bus from avgGrayscale module
wire [7:0] avg_bus_in, sobel_bus_in;

// File I/O declarations

integer infile, outfile;
integer outfile1, outfile2;
integer i,j,k, m;
reg [7:0] in_data [0:3071];
//reg [900*8-1:0]out_data[7:0];

avgGrayscale UUT(
    .rgb_in(rgb_in),
    .clk_i(clk_i),
    .reset(rst_i),
    .rgb_out(rgb_out),
    .flag_grayscale_complete(flag_grayscale_complete),
    .flag_output_complete(flag_output_complete),
    .taken_input(taken_input),
    .gray_output_done(gray_output_done),
    .sobel_output_done(sobel_output_done),
    .avg_bus_in(avg_bus_in),
    .sobel_bus_in(sobel_bus_in)
    );

// clk
initial begin
    clk_i <= 0;
    rgb_in <= 0;
    tmp <= 0;
    tmp2 <= 0;
    i <= 0;
    j <= 0;
    m <= 0;
    forever #5 clk_i <= ~clk_i;
end

initial begin
    #10;
    forever begin
        if(j < 3072) begin
            rgb_in <= in_data[j];
            j <= j + 1;
        end
        else begin
            j <= 1;
            rgb_in <= in_data[0];
        end
        #10;
    end
end

initial begin
    #2;
    rst_i <= 1;
    #5;
    rst_i <= 0;
    infile <= $fopen("input.hex", "r");
    outfile <= $fopen("avg.hex", "w");
    outfile1 <= $fopen("avg_output.hex", "w");
    outfile2 <= $fopen("sobel_output.hex", "w");

    if (infile == 0 || outfile == 0) begin
        $display("Error: Unable to open input or output file.");
        $finish;
    end
    $readmemh("input.hex", in_data);
end

always @(posedge clk_i) begin
    if (taken_input == 1 && gray_output_done == 0) begin
        $display("writing data avg_out_data[%d] = %h", m, avg_bus_in);
        $fwrite(outfile1, "%h\n", avg_bus_in);
    end
    else if (gray_output_done == 1 && sobel_output_done == 0 ) begin
        $display("writing data sobel_out_data[%d] = %h", m, sobel_bus_in);
        $fwrite(outfile2, "%h\n", sobel_bus_in);
    end
end

always @(negedge clk_i) begin
    if(flag_grayscale_complete) begin 
        tmp2 <= 1;
    end 
    if(tmp2) begin
        $fwrite(outfile, "%h\n", rgb_out);
        $display("writing data out_data[%d] = %h", m, rgb_out);
        m <= m + 1;
    end
    if(flag_output_complete) begin
        tmp2 <= 0;
        m<=0;
    end
end
initial begin
    #80650;
    $finish;
end
initial begin
    $dumpfile("avgFilter.vcd");
    $dumpvars(0, tb);
end
endmodule

results/avgFilter.vcd
$date
	Mon Mar 18 19:31:26 2024
$end
$version
	Icarus Verilog
$end
$timescale
	1ps
$end
$scope module tb $end
$var wire 1 ! taken_input $end
$var wire 1 " sobel_output_done $end
$var wire 8 # sobel_bus_in [7:0] $end
$var wire 8 $ rgb_out [7:0] $end
$var wire 1 % gray_output_done $end
$var wire 1 & flag_output_complete $end
$var wire 1 ' flag_grayscale_complete $end
$var wire 8 ( avg_bus_in [7:0] $end
$var reg 1 ) clk_i $end
$var reg 8 * rgb_in [7:0] $end
$var reg 1 + rst_i $end
$var reg 1 , tmp $end
$var reg 1 - tmp2 $end
$var integer 32 . i [31:0] $end
$var integer 32 / infile [31:0] $end
$var integer 32 0 j [31:0] $end
$var integer 32 1 m [31:0] $end
$var integer 32 2 outfile [31:0] $end
$var integer 32 3 outfile1 [31:0] $end
$var integer 32 4 outfile2 [31:0] $end
$scope module UUT $end
$var wire 1 ) clk_i $end
$var wire 1 + reset $end
$var wire 8 5 rgb_in [7:0] $end
$var wire 8 6 rgb_out [7:0] $end
$var wire 8 7 sobel_bus_in [7:0] $end
$var wire 8 8 avg_bus_in [7:0] $end
$var parameter 32 9 res_x $end
$var parameter 32 : res_y $end
$var reg 11 ; a_col [10:0] $end
$var reg 11 < a_row [10:0] $end
$var reg 11 = b_col [10:0] $end
$var reg 11 > b_row [10:0] $end
$var reg 11 ? c_col [10:0] $end
$var reg 11 @ c_row [10:0] $end
$var reg 11 A col [10:0] $end
$var reg 13 B counter [12:0] $end
$var reg 11 C d_col [10:0] $end
$var reg 11 D d_row [10:0] $end
$var reg 1 ' flag_grayscale_complete $end
$var reg 1 & flag_output_complete $end
$var reg 1 % gray_output_done $end
$var reg 11 E row [10:0] $end
$var reg 1 " sobel_output_done $end
$var reg 1 ! taken_input $end
$var integer 32 F i [31:0] $end
$scope module avg $end
$var wire 8 G p0 [7:0] $end
$var wire 8 H p1 [7:0] $end
$var wire 8 I p2 [7:0] $end
$var wire 8 J p3 [7:0] $end
$var wire 8 K p4 [7:0] $end
$var wire 8 L p5 [7:0] $end
$var wire 8 M p6 [7:0] $end
$var wire 8 N p7 [7:0] $end
$var wire 8 O p8 [7:0] $end
$var wire 11 P sum [10:0] $end
$var wire 8 Q out [7:0] $end
$upscope $end
$scope module sobel $end
$var wire 8 R p0 [7:0] $end
$var wire 8 S p1 [7:0] $end
$var wire 8 T p2 [7:0] $end
$var wire 8 U p3 [7:0] $end
$var wire 8 V p5 [7:0] $end
$var wire 8 W p6 [7:0] $end
$var wire 8 X p7 [7:0] $end
$var wire 8 Y p8 [7:0] $end
$var wire 11 Z sum [10:0] $end
$var wire 8 [ out [7:0] $end
$var wire 11 \ gy [10:0] $end
$var wire 11 ] gx [10:0] $end
$var wire 11 ^ abs_gy [10:0] $end
$var wire 11 _ abs_gx [10:0] $end
$upscope $end
$upscope $end
$upscope $end
$enddefinitions $end
$comment Show the parameter values. $end
$dumpall
b100000 :
b100000 9
$end
#0
$dumpvars
bx _
bx ^
bx ]
bx \
bx [
bx Z
bx Y
bx X
bx W
bx V
bx U
bx T
bx S
bx R
bx Q
bx P
bx O
bx N
bx M
bx L
bx K
bx J
bx I
bx H
bx G
bx F
bx E
bx D
bx C
bx B
bx A
bx @
bx ?
bx >
bx =
bx <
bx ;
bx 8
bx 7
bx 6
b0 5
bx 4
bx 3
bx 2
b0 1
b0 0
bx /
b0 .
0-
0,
x+
b0 *
0)
bx (
x'
x&
x%
bx $
bx #
x"
x!
$end
#2000
1+
#5000
0"
0%
0!
0&
0'
b0 C
b0 D
b0 ?
b0 @
b0 =
b0 >
b0 ;
b0 <
b0 A
b0 E
b0 B
1)
#7000
b10000000000000000000000000000110 4
b10000000000000000000000000000101 3
b10000000000000000000000000000100 2
b10000000000000000000000000000011 /
0+
#10000
0)
b1 0
b10011010 *
b10011010 5
#15000
b1 B
1)
#20000
0)
b10 0
b1111110 *
b1111110 5
#25000
b10 B
1)
#30000
0)
b11 0
b1101001 *
b1101001 5
#35000
b11 B
1)
#40000
0)
b100 0
b1100110 *
b1100110 5
#45000
b100 B
1)
#50000
0)
b101 0
b1111101 *
b1111101 5
#55000
b101 B
1)
#60000
0)
b110 0
b10011011 *
b10011011 5
#65000
b110 B
1)
#70000
0)
b111 0
b10101100 *
b10101100 5
#75000
b111 B
1)
#80000
0)
b1000 0
b10110100 *
b10110100 5
#85000
b1000 B
1)
#90000
0)
b1001 0
b10001110 *
b10001110 5
#95000
b1001 B
1)
#100000
0)
b1010 0
b1101111 *
b1101111 5
#105000
b1010 B
1)
#110000
0)
b1011 0
b1101010 *
b1101010 5
#115000
b1011 B
1)
#120000
0)
b1100 0
b1101101 *
b1101101 5
#125000
b1100 B
1)
#130000
0)
b1101 0
b1111011 *
b1111011 5
#135000
b1101 B
1)
#140000
0)
b1110 0
b1111111 *
b1111111 5
#145000
b1110 B
1)
#150000
0)
b1111 0
b10110101 *
b10110101 5
#155000
b1111 B
1)
#160000
0)
b10000 0
b11011001 *
b11011001 5
#165000
b10000 B
1)
#170000
0)
b10001 0
b11010001 *
b11010001 5
#175000
b10001 B
1)
#180000
0)
b10010 0
b10100110 *
b10100110 5
#185000
b10010 B
1)
#190000
0)
b10011 0
b10100100 *
b10100100 5
#195000
b10011 B
1)
#200000
0)
b10100 0
b10011110 *
b10011110 5
#205000
b10100 B
1)
#210000
0)
b10101 0
b1110100 *
b1110100 5
#215000
b10101 B
1)
#220000
0)
b10110 0
b1100110 *
b1100110 5
#225000
b10110 B
1)
#230000
0)
b10111 0
b1011111 *
b1011111 5
#235000
b10111 B
1)
#240000
0)
b11000 0
b1011010 *
b1011010 5
#245000
b11000 B
1)
#250000
0)
b11001 0
b1001000 *
b1001000 5
#255000
b11001 B
1)
#260000
0)
b11010 0
b111100 *
b111100 5
#265000
b11010 B
1)
#270000
0)
b11011 0
b111000 *
b111000 5
#275000
b11011 B
1)
#280000
0)
b11100 0
b1001101 *
b1001101 5
#285000
b11100 B
1)
#290000
0)
b11101 0
b1011110 *
b1011110 5
#295000
b11101 B
1)
#300000
0)
b11110 0
b1011011 *
b1011011 5
#305000
b11110 B
1)
#310000
0)
b11111 0
b1010111 *
b1010111 5
#315000
b11111 B
1)
#320000
0)
b100000 0
b1001111 *
b1001111 5
#325000
b100000 B
1)
#330000
0)
b100001 0
b10001100 *
b10001100 5
#335000
b100001 B
1)
#340000
0)
b100010 0
b10010001 *
b10010001 5
#345000
b100010 B
1)
#350000
0)
b100011 0
b1111101 *
b1111101 5
#355000
b100011 B
1)
#360000
0)
b100100 0
b1111100 *
b1111100 5
#365000
b100100 B
1)
#370000
0)
b100101 0
b10010110 *
b10010110 5
#375000
b100101 B
1)
#380000
0)
b100110 0
b10011000 *
b10011000 5
#385000
b100110 B
1)
#390000
0)
b100111 0
b10101110 *
b10101110 5
#395000
b100111 B
1)
#400000
0)
b101000 0
b10110010 *
b10110010 5
#405000
b101000 B
1)
#410000
0)
b101001 0
b10000110 *
b10000110 5
#415000
b101001 B
1)
#420000
0)
b101010 0
b1101110 *
b1101110 5
#425000
b101010 B
1)
#430000
0)
b101011 0
b10000101 *
b10000101 5
#435000
b101011 B
1)
#440000
0)
b101100 0
b10100011 *
b10100011 5
#445000
b101100 B
1)
#450000
0)
b101101 0
b11000000 *
b11000000 5
#455000
b101101 B
1)
#460000
0)
b101110 0
b11011010 *
b11011010 5
#465000
b101110 B
1)
#470000
0)
b101111 0
b11110000 *
b11110000 5
#475000
b101111 B
1)
#480000
0)
b110000 0
b11110101 *
b11110101 5
#485000
b110000 B
1)
#490000
0)
b110001 0
b11110001 *
b11110001 5
#495000
b110001 B
1)
#500000
0)
b110010 0
b11101110 *
b11101110 5
#505000
b110010 B
1)
#510000
0)
b110011 0
b11101010 *
b11101010 5
#515000
b110011 B
1)
#520000
0)
b110100 0
b11100010 *
b11100010 5
#525000
b110100 B
1)
#530000
0)
b110101 0
b10001110 *
b10001110 5
#535000
b110101 B
1)
#540000
0)
b110110 0
b1100000 *
b1100000 5
#545000
b110110 B
1)
#550000
0)
b110111 0
b1100011 *
b1100011 5
#555000
b110111 B
1)
#560000
0)
b111000 0
b1011111 *
b1011111 5
#565000
b111000 B
1)
#570000
0)
b111001 0
b1011001 *
b1011001 5
#575000
b111001 B
1)
#580000
0)
b111010 0
b1010000 *
b1010000 5
#585000
b111010 B
1)
#590000
0)
b111011 0
b1000001 *
b1000001 5
#595000
b111011 B
1)
#600000
0)
b111100 0
b1010100 *
b1010100 5
#605000
b111100 B
1)
#610000
0)
b111101 0
b1011100 *
b1011100 5
#615000
b111101 B
1)
#620000
0)
b111110 0
b1100000 *
b1100000 5
#625000
b111110 B
1)
#630000
0)
b111111 0
b1001101 *
b1001101 5
#635000
b111111 B
1)
#640000
0)
b1000000 0
b1000111 *
b1000111 5
#645000
b1000000 B
1)
#650000
0)
b1000001 0
b10001100 *
b10001100 5
#655000
b1000001 B
1)
#660000
0)
b1000010 0
b10001011 *
b10001011 5
#665000
b1000010 B
1)
#670000
0)
b1000011 0
b1110011 *
b1110011 5
#675000
b1000011 B
1)
#680000
0)
b1000100 0
b10010011 *
b10010011 5
#685000
b1000100 B
1)
#690000
0)
b1000101 0
b10001010 *
b10001010 5
#695000
b1000101 B
1)
#700000
0)
b1000110 0
b10000100 *
b10000100 5
#705000
b1000110 B
1)
#710000
0)
b1000111 0
b10101010 *
b10101010 5
#715000
b1000111 B
1)
#720000
0)
b1001000 0
b10110010 *
b10110010 5
#725000
b1001000 B
1)
#730000
0)
b1001001 0
b10101011 *
b10101011 5
#735000
b1001001 B
1)
#740000
0)
b1001010 0
b11000000 *
b11000000 5
#745000
b1001010 B
1)
#750000
0)
b1001011 0
b11011011 *
b11011011 5
#755000
b1001011 B
1)
#760000
0)
b1001100 0
b11101010 *
b11101010 5
#765000
b1001100 B
1)
#770000
0)
b1001101 0
b11100101 *
b11100101 5
#775000
b1001101 B
1)
#780000
0)
b1001110 0
b11101111 *
b11101111 5
#785000
b1001110 B
1)
#790000
0)
b1001111 0
b11110100 *
b11110100 5
#795000
b1001111 B
1)
#800000
0)
b1010000 0
b11110110 *
b11110110 5
#805000
b1010000 B
1)
#810000
0)
b1010001 0
b11101000 *
b11101000 5
#815000
b1010001 B
1)
#820000
0)
b1010010 0
b11100001 *
b11100001 5
#825000
b1010010 B
1)
#830000
0)
b1010011 0
b11101011 *
b11101011 5
#835000
b1010011 B
1)
#840000
0)
b1010100 0
b11110011 *
b11110011 5
#845000
b1010100 B
1)
#850000
0)
b1010101 0
b10110001 *
b10110001 5
#855000
b1010101 B
1)
#860000
0)
b1010110 0
b1100101 *
b1100101 5
#865000
b1010110 B
1)
#870000
0)
b1010111 0
#875000
b1010111 B
1)
#880000
0)
b1011000 0
b1011000 *
b1011000 5
#885000
b1011000 B
1)
#890000
0)
b1011001 0
b1100111 *
b1100111 5
#895000
b1011001 B
1)
#900000
0)
b1011010 0
b1011110 *
b1011110 5
#905000
b1011010 B
1)
#910000
0)
b1011011 0
b1000001 *
b1000001 5
#915000
b1011011 B
1)
#920000
0)
b1011100 0
b1010011 *
b1010011 5
#925000
b1011100 B
1)
#930000
0)
b1011101 0
b1011010 *
b1011010 5
#935000
b1011101 B
1)
#940000
0)
b1011110 0
b1001111 *
b1001111 5
#945000
b1011110 B
1)
#950000
0)
b1011111 0
b1000100 *
b1000100 5
#955000
b1011111 B
1)
#960000
0)
b1100000 0
b1000011 *
b1000011 5
#965000
b1100000 B
1)
#970000
0)
b1100001 0
b10001000 *
b10001000 5
#975000
b1100001 B
1)
#980000
0)
b1100010 0
b10001001 *
b10001001 5
#985000
b1100010 B
1)
#990000
0)
b1100011 0
b1111010 *
b1111010 5
#995000
b1100011 B
1)
#1000000
0)
b1100100 0
b10000100 *
b10000100 5
#1005000
b1100100 B
1)
#1010000
0)
b1100101 0
b10010111 *
b10010111 5
#1015000
b1100101 B
1)
#1020000
0)
b1100110 0
b10110101 *
b10110101 5
#1025000
b1100110 B
1)
#1030000
0)
b1100111 0
b11001011 *
b11001011 5
#1035000
b1100111 B
1)
#1040000
0)
b1101000 0
b11010000 *
b11010000 5
#1045000
b1101000 B
1)
#1050000
0)
b1101001 0
#1055000
b1101001 B
1)
#1060000
0)
b1101010 0
b11001011 *
b11001011 5
#1065000
b1101010 B
1)
#1070000
0)
b1101011 0
b10110011 *
b10110011 5
#1075000
b1101011 B
1)
#1080000
0)
b1101100 0
b10101001 *
b10101001 5
#1085000
b1101100 B
1)
#1090000
0)
b1101101 0
b10100100 *
b10100100 5
#1095000
b1101101 B
1)
#1100000
0)
b1101110 0
b1111101 *
b1111101 5
#1105000
b1101110 B
1)
#1110000
0)
b1101111 0
b10110010 *
b10110010 5
#1115000
b1101111 B
1)
#1120000
0)
b1110000 0
b11110000 *
b11110000 5
#1125000
b1110000 B
1)
#1130000
0)
b1110001 0
b11100111 *
b11100111 5
#1135000
b1110001 B
1)
#1140000
0)
b1110010 0
b11010011 *
b11010011 5
#1145000
b1110010 B
1)
#1150000
0)
b1110011 0
b11000011 *
b11000011 5
#1155000
b1110011 B
1)
#1160000
0)
b1110100 0
b11001001 *
b11001001 5
#1165000
b1110100 B
1)
#1170000
0)
b1110101 0
b10110111 *
b10110111 5
#1175000
b1110101 B
1)
#1180000
0)
b1110110 0
b1111001 *
b1111001 5
#1185000
b1110110 B
1)
#1190000
0)
b1110111 0
b1011011 *
b1011011 5
#1195000
b1110111 B
1)
#1200000
0)
b1111000 0
b1011110 *
b1011110 5
#1205000
b1111000 B
1)
#1210000
0)
b1111001 0
b1011011 *
b1011011 5
#1215000
b1111001 B
1)
#1220000
0)
b1111010 0
b1001101 *
b1001101 5
#1225000
b1111010 B
1)
#1230000
0)
b1111011 0
b1000101 *
b1000101 5
#1235000
b1111011 B
1)
#1240000
0)
b1111100 0
b1100001 *
b1100001 5
#1245000
b1111100 B
1)
#1250000
0)
b1111101 0
b1011000 *
b1011000 5
#1255000
b1111101 B
1)
#1260000
0)
b1111110 0
b1001100 *
b1001100 5
#1265000
b1111110 B
1)
#1270000
0)
b1111111 0
b1000000 *
b1000000 5
#1275000
b1111111 B
1)
#1280000
0)
b10000000 0
b1000111 *
b1000111 5
#1285000
b10000000 B
1)
#1290000
0)
b10000001 0
b10000001 *
b10000001 5
#1295000
b10000001 B
1)
#1300000
0)
b10000010 0
b10001101 *
b10001101 5
#1305000
b10000010 B
1)
#1310000
0)
b10000011 0
b10001000 *
b10001000 5
#1315000
b10000011 B
1)
#1320000
0)
b10000100 0
b10111010 *
b10111010 5
#1325000
b10000100 B
1)
#1330000
0)
b10000101 0
b11010111 *
b11010111 5
#1335000
b10000101 B
1)
#1340000
0)
b10000110 0
b11001010 *
b11001010 5
#1345000
b10000110 B
1)
#1350000
0)
b10000111 0
b10100100 *
b10100100 5
#1355000
b10000111 B
1)
#1360000
0)
b10001000 0
b10010110 *
b10010110 5
#1365000
b10001000 B
1)
#1370000
0)
b10001001 0
b10001010 *
b10001010 5
#1375000
b10001001 B
1)
#1380000
0)
b10001010 0
b1110111 *
b1110111 5
#1385000
b10001010 B
1)
#1390000
0)
b10001011 0
b1011110 *
b1011110 5
#1395000
b10001011 B
1)
#1400000
0)
b10001100 0
b1101100 *
b1101100 5
#1405000
b10001100 B
1)
#1410000
0)
b10001101 0
#1415000
b10001101 B
1)
#1420000
0)
b10001110 0
b100000 *
b100000 5
#1425000
b10001110 B
1)
#1430000
0)
b10001111 0
b10000010 *
b10000010 5
#1435000
b10001111 B
1)
#1440000
0)
b10010000 0
b11110001 *
b11110001 5
#1445000
b10010000 B
1)
#1450000
0)
b10010001 0
b11101100 *
b11101100 5
#1455000
b10010001 B
1)
#1460000
0)
b10010010 0
b11101011 *
b11101011 5
#1465000
b10010010 B
1)
#1470000
0)
b10010011 0
b11010011 *
b11010011 5
#1475000
b10010011 B
1)
#1480000
0)
b10010100 0
b11000011 *
b11000011 5
#1485000
b10010100 B
1)
#1490000
0)
b10010101 0
b10000101 *
b10000101 5
#1495000
b10010101 B
1)
#1500000
0)
b10010110 0
b1111101 *
b1111101 5
#1505000
b10010110 B
1)
#1510000
0)
b10010111 0
b1100110 *
b1100110 5
#1515000
b10010111 B
1)
#1520000
0)
b10011000 0
b1100010 *
b1100010 5
#1525000
b10011000 B
1)
#1530000
0)
b10011001 0
b1011000 *
b1011000 5
#1535000
b10011001 B
1)
#1540000
0)
b10011010 0
b1010000 *
b1010000 5
#1545000
b10011010 B
1)
#1550000
0)
b10011011 0
b1011010 *
b1011010 5
#1555000
b10011011 B
1)
#1560000
0)
b10011100 0
b1011110 *
b1011110 5
#1565000
b10011100 B
1)
#1570000
0)
b10011101 0
b1000101 *
b1000101 5
#1575000
b10011101 B
1)
#1580000
0)
b10011110 0
b1000111 *
b1000111 5
#1585000
b10011110 B
1)
#1590000
0)
b10011111 0
b1000100 *
b1000100 5
#1595000
b10011111 B
1)
#1600000
0)
b10100000 0
b1010111 *
b1010111 5
#1605000
b10100000 B
1)
#1610000
0)
b10100001 0
b10001000 *
b10001000 5
#1615000
b10100001 B
1)
#1620000
0)
b10100010 0
#1625000
b10100010 B
1)
#1630000
0)
b10100011 0
b1111111 *
b1111111 5
#1635000
b10100011 B
1)
#1640000
0)
b10100100 0
b10011001 *
b10011001 5
#1645000
b10100100 B
1)
#1650000
0)
b10100101 0
b10001010 *
b10001010 5
#1655000
b10100101 B
1)
#1660000
0)
b10100110 0
b1111000 *
b1111000 5
#1665000
b10100110 B
1)
#1670000
0)
b10100111 0
b1011101 *
b1011101 5
#1675000
b10100111 B
1)
#1680000
0)
b10101000 0
b1100010 *
b1100010 5
#1685000
b10101000 B
1)
#1690000
0)
b10101001 0
b1100111 *
b1100111 5
#1695000
b10101001 B
1)
#1700000
0)
b10101010 0
b1100000 *
b1100000 5
#1705000
b10101010 B
1)
#1710000
0)
b10101011 0
b1010110 *
b1010110 5
#1715000
b10101011 B
1)
#1720000
0)
b10101100 0
b1110111 *
b1110111 5
#1725000
b10101100 B
1)
#1730000
0)
b10101101 0
b1100001 *
b1100001 5
#1735000
b10101101 B
1)
#1740000
0)
b10101110 0
b101110 *
b101110 5
#1745000
b10101110 B
1)
#1750000
0)
b10101111 0
b1110101 *
b1110101 5
#1755000
b10101111 B
1)
#1760000
0)
b10110000 0
b11001011 *
b11001011 5
#1765000
b10110000 B
1)
#1770000
0)
b10110001 0
b11100100 *
b11100100 5
#1775000
b10110001 B
1)
#1780000
0)
b10110010 0
b11101001 *
b11101001 5
#1785000
b10110010 B
1)
#1790000
0)
b10110011 0
b11101100 *
b11101100 5
#1795000
b10110011 B
1)
#1800000
0)
b10110100 0
b11101101 *
b11101101 5
#1805000
b10110100 B
1)
#1810000
0)
b10110101 0
b10100101 *
b10100101 5
#1815000
b10110101 B
1)
#1820000
0)
b10110110 0
b1111110 *
b1111110 5
#1825000
b10110110 B
1)
#1830000
0)
b10110111 0
b1111100 *
b1111100 5
#1835000
b10110111 B
1)
#1840000
0)
b10111000 0
b1011100 *
b1011100 5
#1845000
b10111000 B
1)
#1850000
0)
b10111001 0
b1011000 *
b1011000 5
#1855000
b10111001 B
1)
#1860000
0)
b10111010 0
b1001110 *
b1001110 5
#1865000
b10111010 B
1)
#1870000
0)
b10111011 0
b1010111 *
b1010111 5
#1875000
b10111011 B
1)
#1880000
0)
b10111100 0
b1100010 *
b1100010 5
#1885000
b10111100 B
1)
#1890000
0)
b10111101 0
b1001100 *
b1001100 5
#1895000
b10111101 B
1)
#1900000
0)
b10111110 0
b1000011 *
b1000011 5
#1905000
b10111110 B
1)
#1910000
0)
b10111111 0
b1010001 *
b1010001 5
#1915000
b10111111 B
1)
